krnel/__init__.py
krnel-0.0.15.dist-info/licenses/LICENSE
krnel-0.0.15.dist-info/METADATA
krnel-0.0.15.dist-info/WHEEL
krnel-0.0.15.dist-info/entry_points.txt
krnel-0.0.15.dist-info/top_level.txt
krnel-0.0.15.dist-info/RECORD
