Metadata-Version: 2.4
Name: krnel
Version: 0.0.15
Summary: Krnel client library
Author-email: Kimberly Wilber <kimmy+pypispam@krnel.ai>, Peyman Faratin <peyman+pypispam@krnel.ai>
Requires-Python: >=3.11
License-File: LICENSE
Requires-Dist: httpx>=0.28.1
Requires-Dist: pydantic>=2.11.7
Dynamic: license-file
